Metadata-Version: 2.1
Name: rainbowchar
Version: 1.1
Summary: RainbowChar is a lib that stylizes text by formatting in ANSI escape code. It only supports true color terminals.
Home-page: https://github.com/roderiano/rainbow-char-lib
Author: Gabriel da Rosa Silveira
Author-email: gabrielsilveirapro@gmail.com
License: MIT
Download-URL: https://github.com/roderiano/rainbow-char-lib/archive/refs/tags/v1.1.tar.gz
Platform: UNKNOWN
